hoppr_jq_filter/__init__.py
hoppr_jq_filter/plugin.py
hoppr_jq_filter/py.typed
hoppr_jq_filter/renovate.json
hoppr_jq_filter-0.2.5.dist-info/LICENSE
hoppr_jq_filter-0.2.5.dist-info/METADATA
hoppr_jq_filter-0.2.5.dist-info/WHEEL
hoppr_jq_filter-0.2.5.dist-info/entry_points.txt
hoppr_jq_filter-0.2.5.dist-info/RECORD
