Metadata-Version: 2.1
Name: hoppr_jq_filter
Version: 0.2.5
Summary: Starter Plug-in for Hoppr
Home-page: https://hoppr.dev/
License: MIT
Keywords: hoppr,plugin,packaging,reports,build dependencies,software bill of materials
Author: LMCO Open Source
Author-email: open.source@lmco.com
Requires-Python: >=3.10,<4.0
Classifier: Development Status :: 2 - Pre-Alpha
Classifier: Framework :: Pytest
Classifier: Intended Audience :: Developers
Classifier: Intended Audience :: Information Technology
Classifier: Intended Audience :: System Administrators
Classifier: License :: OSI Approved :: MIT License
Classifier: Programming Language :: Python
Classifier: Programming Language :: Python :: 3
Classifier: Programming Language :: Python :: 3.10
Classifier: Programming Language :: Python :: 3.11
Classifier: Programming Language :: Python :: 3.12
Classifier: Topic :: Communications :: File Sharing
Classifier: Topic :: Security
Classifier: Topic :: Software Development :: Version Control
Classifier: Topic :: System :: Archiving :: Packaging
Classifier: Topic :: System :: Software Distribution
Classifier: Typing :: Typed
Requires-Dist: hoppr (>=1.9.0,<2.0.0)
Requires-Dist: jq (>=1.4.0,<2.0.0)
